pontyredis/__init__.py
pontyredis/cache.py
pontyredis/lock.py
pontyredis/provider.py
pontyredis/py.typed
pontyredis-0.2.2.dist-info/METADATA
pontyredis-0.2.2.dist-info/WHEEL
pontyredis-0.2.2.dist-info/top_level.txt
pontyredis-0.2.2.dist-info/RECORD
